[
{
"acceleration": 1.2192000000000003,
"curvature": 0.0,
"pose": {
"rotation": {
"radians": 0.0
},
"translation": {
"x": 0.0,
"y": 8.2296
}
},
"time": 0.0,
"velocity": 0.0
},
{
"acceleration": 1.2192000000000005,
"curvature": 0.0,
"pose": {
"rotation": {
"radians": 0.0
},
"translation": {
"x": 0.06560118064284325,
"y": 8.2296
}
},
"time": 0.32804494403435236,
"velocity": 0.39995239576668246
},
{
"acceleration": 1.2192000000000007,
"curvature": 0.0,
"pose": {
"rotation": {
"radians": 0.0
},
"translation": {
"x": 0.13854350566864013,
"y": 8.2296
}
},
"time": 0.4767279415938671,
"velocity": 0.581226706391243
},
{
"acceleration": 1.2191999999999996,
"curvature": 0.0,
"pose": {
"rotation": {
"radians": 0.0
},
"translation": {
"x": 0.22482817581295966,
"y": 8.2296
}
},
"time": 0.6072994519716703,
"velocity": 0.7404194918438608
},
{
"acceleration": 1.2191999999999998,
"curvature": 0.0,
"pose": {
"rotation": {
"radians": 0.0
},
"translation": {
"x": 0.32908456420898435,
"y": 8.2296
}
},
"time": 0.7347359277624319,
"velocity": 0.8957900431279573
},
{
"acceleration": 1.2191999999999996,
"curvature": 0.0,
"pose": {
"rotation": {
"radians": 0.0
},
"translation": {
"x": 0.4546691384017467,
"y": 8.2296
}
},
"time": 0.8636251062526186,
"velocity": 1.0529317295431928
},
{
"acceleration": 1.2192000000000016,
"curvature": 0.0,
"pose": {
"rotation": {
"radians": 0.0
},
"translation": {
"x": 0.5261846752474084,
"y": 8.2296
}
},
"time": 0.9290661103216018,
"velocity": 1.132717401704097
},
{
"acceleration": 1.2192,
"curvature": 0.0,
"pose": {
"rotation": {
"radians": 0.0
},
"translation": {
"x": 0.6037643823623657,
"y": 8.2296
}
},
"time": 0.9952020580873029,
"velocity": 1.21335034922004
},
{
"acceleration": 1.2191999999999996,
"curvature": 0.0,
"pose": {
"rotation": {
"radians": 0.0
},
"translation": {
"x": 0.687513864702545,
"y": 8.2296
}
},
"time": 1.0619846787244072,
"velocity": 1.2947717203007973
},
{
"acceleration": 1.2192000000000012,
"curvature": 0.0,
"pose": {
"rotation": {
"radians": 0.0
},
"translation": {
"x": 0.7774777185022831,
"y": 8.2296
}
},
"time": 1.1293316422437816,
"velocity": 1.3768811382236186
},
{
"acceleration": 0.9398335826241175,
"curvature": 0.0,
"pose": {
"rotation": {
"radians": 0.0
},
"translation": {
"x": 0.873642622587271,
"y": 8.2296
}
},
"time": 1.1971385822385419,
"velocity": 1.4595513594652303
},
{
"acceleration": 0.0,
"curvature": 0.0,
"pose": {
"rotation": {
"radians": 0.0
},
"translation": {
"x": 0.9759404296874999,
"y": 8.2296
}
},
"time": 1.2657131062035423,
"velocity": 1.524
},
{
"acceleration": 0.0,
"curvature": 0.0,
"pose": {
"rotation": {
"radians": 0.0
},
"translation": {
"x": 1.0842512577502057,
"y": 8.2296
}
},
"time": 1.3367832033575486,
"velocity": 1.524
},
{
"acceleration": 0.0,
"curvature": 0.0,
"pose": {
"rotation": {
"radians": 0.0
},
"translation": {
"x": 1.1984065812528133,
"y": 8.2296
}
},
"time": 1.4116882712726455,
"velocity": 1.524
},
{
"acceleration": 0.0,
"curvature": 0.0,
"pose": {
"rotation": {
"radians": 0.0
},
"translation": {
"x": 1.3181923225158823,
"y": 8.2296
}
},
"time": 1.4902878390305647,
"velocity": 1.524
},
{
"acceleration": 0.0,
"curvature": 0.0,
"pose": {
"rotation": {
"radians": 0.0
},
"translation": {
"x": 1.4433519430160522,
"y": 8.2296
}
},
"time": 1.5724135742668968,
"velocity": 1.524
},
{
"acceleration": 0.0,
"curvature": 0.0,
"pose": {
"rotation": {
"radians": 0.0
},
"translation": {
"x": 1.5078559400572848,
"y": 8.2296
}
},
"time": 1.6147390316430337,
"velocity": 1.524
},
{
"acceleration": 0.0,
"curvature": 0.0,
"pose": {
"rotation": {
"radians": 0.0
},
"translation": {
"x": 1.5735895346989854,
"y": 8.2296
}
},
"time": 1.6578713115916561,
"velocity": 1.524
},
{
"acceleration": 0.0,
"curvature": 0.0,
"pose": {
"rotation": {
"radians": 0.0
},
"translation": {
"x": 1.640510094113677,
"y": 8.2296
}
},
"time": 1.7017824398165193,
"velocity": 1.524
},
{
"acceleration": 0.0,
"curvature": 0.0,
"pose": {
"rotation": {
"radians": 0.0
},
"translation": {
"x": 1.7085729112923145,
"y": 8.2296
}
},
"time": 1.746443081009851,
"velocity": 1.524
},
{
"acceleration": 0.0,
"curvature": 0.0,
"pose": {
"rotation": {
"radians": 0.0
},
"translation": {
"x": 1.7777313016478147,
"y": 8.2296
}
},
"time": 1.7918226022404942,
"velocity": 1.524
},
{
"acceleration": 0.0,
"curvature": 0.0,
"pose": {
"rotation": {
"radians": 0.0
},
"translation": {
"x": 1.8479366996185855,
"y": 8.2296
}
},
"time": 1.8378891363420498,
"velocity": 1.524
},
{
"acceleration": 0.0,
"curvature": 0.0,
"pose": {
"rotation": {
"radians": 0.0
},
"translation": {
"x": 1.919138755272055,
"y": 8.2296
}
},
"time": 1.8846096453010193,
"velocity": 1.524
},
{
"acceleration": 0.0,
"curvature": 0.0,
"pose": {
"rotation": {
"radians": 0.0
},
"translation": {
"x": 1.9912854309082033,
"y": 8.2296
}
},
"time": 1.9319499836449487,
"velocity": 1.524
},
{
"acceleration": 0.0,
"curvature": 0.0,
"pose": {
"rotation": {
"radians": 0.0
},
"translation": {
"x": 2.0643230976630873,
"y": 8.2296
}
},
"time": 1.9798749618305682,
"velocity": 1.524
},
{
"acceleration": 0.0,
"curvature": 0.0,
"pose": {
"rotation": {
"radians": 0.0
},
"translation": {
"x": 2.1381966321123764,
"y": 8.2296
}
},
"time": 2.028348409631939,
"velocity": 1.524
},
{
"acceleration": 0.0,
"curvature": 0.0,
"pose": {
"rotation": {
"radians": 0.0
},
"translation": {
"x": 2.212849512874876,
"y": 8.2296
}
},
"time": 2.0773332395285924,
"velocity": 1.524
},
{
"acceleration": 0.0,
"curvature": 0.0,
"pose": {
"rotation": {
"radians": 0.0
},
"translation": {
"x": 2.2882239172160626,
"y": 8.2296
}
},
"time": 2.126791510093675,
"velocity": 1.524
},
{
"acceleration": 0.0,
"curvature": 0.0,
"pose": {
"rotation": {
"radians": 0.0
},
"translation": {
"x": 2.3642608176516076,
"y": 8.2296
}
},
"time": 2.1766844893820907,
"velocity": 1.524
},
{
"acceleration": 0.0,
"curvature": 0.0,
"pose": {
"rotation": {
"radians": 0.0
},
"translation": {
"x": 2.4409000785509125,
"y": 8.2296
}
},
"time": 2.2269727183186423,
"velocity": 1.524
},
{
"acceleration": 0.0,
"curvature": 0.0,
"pose": {
"rotation": {
"radians": 0.0
},
"translation": {
"x": 2.5180805527406336,
"y": 8.2296
}
},
"time": 2.277616074086176,
"velocity": 1.524
},
{
"acceleration": 0.0,
"curvature": 0.0,
"pose": {
"rotation": {
"radians": 0.0
},
"translation": {
"x": 2.5957401781082154,
"y": 8.2296
}
},
"time": 2.328573833513723,
"velocity": 1.524
},
{
"acceleration": 0.0,
"curvature": 0.0,
"pose": {
"rotation": {
"radians": 0.0
},
"translation": {
"x": 2.673816074205417,
"y": 8.2296
}
},
"time": 2.3798047364646426,
"velocity": 1.524
},
{
"acceleration": 0.0,
"curvature": 0.0,
"pose": {
"rotation": {
"radians": 0.0
},
"translation": {
"x": 2.752244638851844,
"y": 8.2296
}
},
"time": 2.431267049224765,
"velocity": 1.524
},
{
"acceleration": 0.0,
"curvature": 0.0,
"pose": {
"rotation": {
"radians": 0.0
},
"translation": {
"x": 2.8309616447384762,
"y": 8.2296
}
},
"time": 2.4829186278905344,
"velocity": 1.524
},
{
"acceleration": 0.0,
"curvature": 0.0,
"pose": {
"rotation": {
"radians": 0.0
},
"translation": {
"x": 2.909902336031198,
"y": 8.2296
}
},
"time": 2.5347169817571498,
"velocity": 1.524
},
{
"acceleration": 0.0,
"curvature": 0.0,
"pose": {
"rotation": {
"radians": 0.0
},
"translation": {
"x": 2.9890015249743302,
"y": 8.2296
}
},
"time": 2.5866193367067116,
"velocity": 1.524
},
{
"acceleration": 0.0,
"curvature": 0.0,
"pose": {
"rotation": {
"radians": 0.0
},
"translation": {
"x": 3.068193688494153,
"y": 8.2296
}
},
"time": 2.6385826985963594,
"velocity": 1.524
},
{
"acceleration": 0.0,
"curvature": 0.0,
"pose": {
"rotation": {
"radians": 0.0
},
"translation": {
"x": 3.1474130648024436,
"y": 8.2296
}
},
"time": 2.690563916646419,
"velocity": 1.524
},
{
"acceleration": 0.0,
"curvature": 0.0,
"pose": {
"rotation": {
"radians": 0.0
},
"translation": {
"x": 3.22659375,
"y": 8.2296
}
},
"time": 2.7425197468285427,
"velocity": 1.524
},
{
"acceleration": 0.0,
"curvature": 0.0,
"pose": {
"rotation": {
"radians": 0.0
},
"translation": {
"x": 3.3056697946801723,
"y": 8.2296
}
},
"time": 2.7944069152538527,
"velocity": 1.524
},
{
"acceleration": 0.0,
"curvature": 0.0,
"pose": {
"rotation": {
"radians": 0.0
},
"translation": {
"x": 3.3845753005323935,
"y": 8.2296
}
},
"time": 2.8461821815610846,
"velocity": 1.524
},
{
"acceleration": 0.0,
"curvature": 0.0,
"pose": {
"rotation": {
"radians": 0.0
},
"translation": {
"x": 3.463244516945706,
"y": 8.2296
}
},
"time": 2.8978024023047277,
"velocity": 1.524
},
{
"acceleration": 0.0,
"curvature": 0.0,
"pose": {
"rotation": {
"radians": 0.0
},
"translation": {
"x": 3.541611937612295,
"y": 8.2296
}
},
"time": 2.949224594343172,
"velocity": 1.524
},
{
"acceleration": 0.0,
"curvature": 0.0,
"pose": {
"rotation": {
"radians": 0.0
},
"translation": {
"x": 3.6196123971310152,
"y": 8.2296
}
},
"time": 3.0004059982268467,
"velocity": 1.524
},
{
"acceleration": 0.0,
"curvature": 0.0,
"pose": {
"rotation": {
"radians": 0.0
},
"translation": {
"x": 3.697181167610921,
"y": 8.2296
}
},
"time": 3.051304141586365,
"velocity": 1.524
},
{
"acceleration": 0.0,
"curvature": 0.0,
"pose": {
"rotation": {
"radians": 0.0
},
"translation": {
"x": 3.774254055274796,
"y": 8.2296
}
},
"time": 3.1018769025206656,
"velocity": 1.524
},
{
"acceleration": 0.0,
"curvature": 0.0,
"pose": {
"rotation": {
"radians": 0.0
},
"translation": {
"x": 3.850767497062683,
"y": 8.2296
}
},
"time": 3.1520825729851585,
"velocity": 1.524
},
{
"acceleration": 0.0,
"curvature": 0.0,
"pose": {
"rotation": {
"radians": 0.0
},
"translation": {
"x": 3.9266586572354134,
"y": 8.2296
}
},
"time": 3.2018799221798635,
"velocity": 1.524
},
{
"acceleration": 0.0,
"curvature": 0.0,
"pose": {
"rotation": {
"radians": 0.0
},
"translation": {
"x": 4.001865523978137,
"y": 8.2296
}
},
"time": 3.251228259937556,
"velocity": 1.524
},
{
"acceleration": 0.0,
"curvature": 0.0,
"pose": {
"rotation": {
"radians": 0.0
},
"translation": {
"x": 4.076327006003848,
"y": 8.2296
}
},
"time": 3.3000875001119074,
"velocity": 1.524
},
{
"acceleration": 0.0,
"curvature": 0.0,
"pose": {
"rotation": {
"radians": 0.0
},
"translation": {
"x": 4.149983029156923,
"y": 8.2296
}
},
"time": 3.348418223965631,
"velocity": 1.524
},
{
"acceleration": 0.0,
"curvature": 0.0,
"pose": {
"rotation": {
"radians": 0.0
},
"translation": {
"x": 4.222774633016642,
"y": 8.2296
}
},
"time": 3.3961817435586226,
"velocity": 1.524
},
{
"acceleration": 0.0,
"curvature": 0.0,
"pose": {
"rotation": {
"radians": 0.0
},
"translation": {
"x": 4.294644067500718,
"y": 8.2296
}
},
"time": 3.4433401651361,
"velocity": 1.524
},
{
"acceleration": 0.0,
"curvature": 0.0,
"pose": {
"rotation": {
"radians": 0.0
},
"translation": {
"x": 4.365534889468836,
"y": 8.2296
}
},
"time": 3.489856452516755,
"velocity": 1.524
},
{
"acceleration": 0.0,
"curvature": 0.0,
"pose": {
"rotation": {
"radians": 0.0
},
"translation": {
"x": 4.435392059326172,
"y": 8.2296
}
},
"time": 3.535694490480886,
"velocity": 1.524
},
{
"acceleration": 0.0,
"curvature": 0.0,
"pose": {
"rotation": {
"radians": 0.0
},
"translation": {
"x": 4.504162037626928,
"y": 8.2296
}
},
"time": 3.5808191481585476,
"velocity": 1.524
},
{
"acceleration": 0.0,
"curvature": 0.0,
"pose": {
"rotation": {
"radians": 0.0
},
"translation": {
"x": 4.571792881677858,
"y": 8.2296
}
},
"time": 3.625196342417688,
"velocity": 1.524
},
{
"acceleration": 0.0,
"curvature": 0.0,
"pose": {
"rotation": {
"radians": 0.0
},
"translation": {
"x": 4.638234342141804,
"y": 8.2296
}
},
"time": 3.668793101252298,
"velocity": 1.524
},
{
"acceleration": 0.0,
"curvature": 0.0,
"pose": {
"rotation": {
"radians": 0.0
},
"translation": {
"x": 4.703437959641217,
"y": 8.2296
}
},
"time": 3.711577627170548,
"velocity": 1.524
},
{
"acceleration": 0.0,
"curvature": 0.0,
"pose": {
"rotation": {
"radians": 0.0
},
"translation": {
"x": 4.829947357655504,
"y": 8.2296
}
},
"time": 3.7945890431904212,
"velocity": 1.524
},
{
"acceleration": 0.0,
"curvature": 0.0,
"pose": {
"rotation": {
"radians": 0.0
},
"translation": {
"x": 4.95097287082672,
"y": 8.2296
}
},
"time": 3.8740021095757338,
"velocity": 1.524
},
{
"acceleration": -0.3558189322358009,
"curvature": 0.0,
"pose": {
"rotation": {
"radians": 0.0
},
"translation": {
"x": 5.066201116240583,
"y": 8.2296
}
},
"time": 3.9496111944929666,
"velocity": 1.524
},
{
"acceleration": -1.219200000000002,
"curvature": 0.0,
"pose": {
"rotation": {
"radians": 0.0
},
"translation": {
"x": 5.175356624275446,
"y": 8.2296
}
},
"time": 4.021844646728857,
"velocity": 1.4982979701537198
},
{
"acceleration": -1.2192000000000007,
"curvature": 0.0,
"pose": {
"rotation": {
"radians": 0.0
},
"translation": {
"x": 5.278204929915255,
"y": 8.2296
}
},
"time": 4.092520370138021,
"velocity": 1.4121301281732672
},
{
"acceleration": -1.2192000000000016,
"curvature": 0.0,
"pose": {
"rotation": {
"radians": 0.0
},
"translation": {
"x": 5.374555664062501,
"y": 8.2296
}
},
"time": 4.162888739904025,
"velocity": 1.326337011754555
},
{
"acceleration": -1.2191999999999996,
"curvature": 0.0,
"pose": {
"rotation": {
"radians": 0.0
},
"translation": {
"x": 5.464265644851139,
"y": 8.2296
}
},
"time": 4.232770639696933,
"velocity": 1.2411369995270416
},
{
"acceleration": -1.2192000000000016,
"curvature": 0.0,
"pose": {
"rotation": {
"radians": 0.0
},
"translation": {
"x": 5.54724196895957,
"y": 8.2296
}
},
"time": 4.301978245991103,
"velocity": 1.15675908593319
},
{
"acceleration": -1.2191999999999987,
"curvature": 0.0,
"pose": {
"rotation": {
"radians": 0.0
},
"translation": {
"x": 5.62344510292355,
"y": 8.2296
}
},
"time": 4.370315699790444,
"velocity": 1.0734420622610334
},
{
"acceleration": -1.2191999999999998,
"curvature": 0.0,
"pose": {
"rotation": {
"radians": 0.0
},
"translation": {
"x": 5.692891974449158,
"y": 8.2296
}
},
"time": 4.43758067488989,
"velocity": 0.9914326046197882
},
{
"acceleration": -1.2192,
"curvature": 0.0,
"pose": {
"rotation": {
"radians": 0.0
},
"translation": {
"x": 5.811885494738817,
"y": 8.2296
}
},
"time": 4.568072512025335,
"velocity": 0.8323369567842538
},
{
"acceleration": -1.2192000000000003,
"curvature": 0.0,
"pose": {
"rotation": {
"radians": 0.0
},
"translation": {
"x": 5.905604644775393,
"y": 8.2296
}
},
"time": 4.69190015082259,
"velocity": 0.6813662995626402
},
{
"acceleration": -1.2192,
"curvature": 0.0,
"pose": {
"rotation": {
"radians": 0.0
},
"translation": {
"x": 6.028353329658508,
"y": 8.2296
}
},
"time": 4.9176435659748545,
"velocity": 0.40613992780899966
},
{
"acceleration": -1.2192,
"curvature": 0.0,
"pose": {
"rotation": {
"radians": 0.0
},
"translation": {
"x": 6.096000000000002,
"y": 8.2296
}
},
"time": 5.2507635855032335,
"velocity": 0.0
}
]